wat/__init__.py
wat/py.typed
wat/version.py
wat/inspection/__init__.py
wat/inspection/inspection.py
wat_inspector-0.4.3.dist-info/LICENSE
wat_inspector-0.4.3.dist-info/METADATA
wat_inspector-0.4.3.dist-info/WHEEL
wat_inspector-0.4.3.dist-info/top_level.txt
wat_inspector-0.4.3.dist-info/RECORD
