Metadata-Version: 2.1
Name: wat-inspector
Version: 0.4.3
Summary: Deep inspection of Python objects
Author-email: igrek51 <igrek51.dev@gmail.com>
License: MIT
Project-URL: Homepage, https://github.com/igrek51/wat
Classifier: Programming Language :: Python :: 3
Classifier: License :: OSI Approved :: MIT License
Classifier: Operating System :: OS Independent
Requires-Python: >=3.8
License-File: LICENSE
